{
  "T>0.0C_P>0.5mm": {
    "T_thresh": 0.0,
    "P_thresh": 0.5,
    "SSW_events": 94,
    "SSW_days": 517,
    "ctrl_events": 412,
    "ctrl_days": 2205,
    "RR": 0.973,
    "pct_change": -2.7,
    "chi2": 0.04,
    "P": 0.8401
  },
  "T>0.0C_P>1.0mm": {
    "T_thresh": 0.0,
    "P_thresh": 1.0,
    "SSW_events": 50,
    "SSW_days": 517,
    "ctrl_events": 210,
    "ctrl_days": 2205,
    "RR": 1.015,
    "pct_change": 1.5,
    "chi2": 0.0,
    "P": 0.9845
  },
  "T>0.0C_P>2.0mm": {
    "T_thresh": 0.0,
    "P_thresh": 2.0,
    "SSW_events": 12,
    "SSW_days": 517,
    "ctrl_events": 72,
    "ctrl_days": 2205,
    "RR": 0.711,
    "pct_change": -28.9,
    "chi2": 0.95,
    "P": 0.329
  },
  "T>0.5C_P>0.5mm": {
    "T_thresh": 0.5,
    "P_thresh": 0.5,
    "SSW_events": 82,
    "SSW_days": 517,
    "ctrl_events": 396,
    "ctrl_days": 2205,
    "RR": 0.883,
    "pct_change": -11.7,
    "chi2": 1.13,
    "P": 0.2871
  },
  "T>0.5C_P>1.0mm": {
    "T_thresh": 0.5,
    "P_thresh": 1.0,
    "SSW_events": 43,
    "SSW_days": 517,
    "ctrl_events": 203,
    "ctrl_days": 2205,
    "RR": 0.903,
    "pct_change": -9.7,
    "chi2": 0.3,
    "P": 0.5827
  },
  "T>0.5C_P>2.0mm": {
    "T_thresh": 0.5,
    "P_thresh": 2.0,
    "SSW_events": 10,
    "SSW_days": 517,
    "ctrl_events": 70,
    "ctrl_days": 2205,
    "RR": 0.609,
    "pct_change": -39.1,
    "chi2": 1.84,
    "P": 0.1744
  },
  "T>1.0C_P>0.5mm": {
    "T_thresh": 1.0,
    "P_thresh": 0.5,
    "SSW_events": 76,
    "SSW_days": 517,
    "ctrl_events": 366,
    "ctrl_days": 2205,
    "RR": 0.886,
    "pct_change": -11.4,
    "chi2": 0.97,
    "P": 0.3235
  },
  "T>1.0C_P>1.0mm": {
    "T_thresh": 1.0,
    "P_thresh": 1.0,
    "SSW_events": 42,
    "SSW_days": 517,
    "ctrl_events": 188,
    "ctrl_days": 2205,
    "RR": 0.953,
    "pct_change": -4.7,
    "chi2": 0.04,
    "P": 0.8351
  },
  "T>1.0C_P>2.0mm": {
    "T_thresh": 1.0,
    "P_thresh": 2.0,
    "SSW_events": 9,
    "SSW_days": 517,
    "ctrl_events": 67,
    "ctrl_days": 2205,
    "RR": 0.573,
    "pct_change": -42.7,
    "chi2": 2.14,
    "P": 0.1433
  },
  "T>2.0C_P>0.5mm": {
    "T_thresh": 2.0,
    "P_thresh": 0.5,
    "SSW_events": 57,
    "SSW_days": 517,
    "ctrl_events": 296,
    "ctrl_days": 2205,
    "RR": 0.821,
    "pct_change": -17.9,
    "chi2": 1.93,
    "P": 0.165
  },
  "T>2.0C_P>1.0mm": {
    "T_thresh": 2.0,
    "P_thresh": 1.0,
    "SSW_events": 28,
    "SSW_days": 517,
    "ctrl_events": 153,
    "ctrl_days": 2205,
    "RR": 0.781,
    "pct_change": -21.9,
    "chi2": 1.33,
    "P": 0.249
  },
  "T>2.0C_P>2.0mm": {
    "T_thresh": 2.0,
    "P_thresh": 2.0,
    "SSW_events": 6,
    "SSW_days": 517,
    "ctrl_events": 54,
    "ctrl_days": 2205,
    "RR": 0.474,
    "pct_change": -52.6,
    "chi2": 2.66,
    "P": 0.1032
  }
}